pingupricewatch/__init__.py
pingupricewatch/database.py
pingupricewatch/models.py
pingupricewatch/prices.py
pingupricewatch-0.1.0.dist-info/LICENSE
pingupricewatch-0.1.0.dist-info/METADATA
pingupricewatch-0.1.0.dist-info/WHEEL
pingupricewatch-0.1.0.dist-info/RECORD
