Metadata-Version: 2.1
Name: pingupricewatch
Version: 0.1.0
Summary: 
Home-page: https://codeberg.org/PinguPriceWatch/PinguPriceWatch
Author: Pinguin
Author-email: ponguout@posteo.net
Requires-Python: >=3.11,<4.0
Classifier: Programming Language :: Python :: 3
Classifier: Programming Language :: Python :: 3.11
Classifier: Programming Language :: Python :: 3.12
Requires-Dist: bs4 (>=0.0.2,<0.0.3)
Requires-Dist: pydantic (>=2.7.1,<3.0.0)
Requires-Dist: requests (>=2.31.0,<3.0.0)
Project-URL: Repository, https://codeberg.org/PinguPriceWatch/PinguPriceWatch
